downkedin/__init__.py
downkedin/downloader.py
downkedin/exceptions.py
downkedin/fetcher.py
downkedin/filemanager.py
downkedin/login.py
downkedin/models.py
downkedin/parser.py
downkedin-0.1.1.dist-info/WHEEL
downkedin-0.1.1.dist-info/METADATA
downkedin-0.1.1.dist-info/RECORD
