Metadata-Version: 2.1
Name: downkedin
Version: 0.1.1
Summary: 
Author: tiagovla
Author-email: tiagovla@gmail.com
Requires-Python: >=3.8,<4.0
Classifier: Programming Language :: Python :: 3
Classifier: Programming Language :: Python :: 3.8
Classifier: Programming Language :: Python :: 3.9
Requires-Dist: aiofiles (>=0.7.0,<0.8.0)
Requires-Dist: aiohttp (>=3.7.4,<4.0.0)
Requires-Dist: lxml (>=4.6.3,<5.0.0)
Requires-Dist: requests (>=2.26.0,<3.0.0)
Requires-Dist: tqdm (>=4.62.3,<5.0.0)
